mqt/qao/__init__.py
mqt/qao/constraints.py
mqt/qao/objectivefunction.py
mqt/qao/problem.py
mqt/qao/solvers.py
mqt/qao/variables.py
mqt/qao/karp/__init__.py
mqt/qao/karp/karp_graphs.py
mqt/qao/karp/karp_number.py
mqt/qao/karp/karp_sets.py
mqt/qao/model/RandomForest/Scaler.pkl
mqt/qao/model/RandomForest/ScalerKCross.pkl
mqt/qao/model/RandomForest/model.pkl
mqt.qao-0.3.0.dist-info/LICENSE
mqt.qao-0.3.0.dist-info/METADATA
mqt.qao-0.3.0.dist-info/WHEEL
mqt.qao-0.3.0.dist-info/top_level.txt
mqt.qao-0.3.0.dist-info/RECORD
