Metadata-Version: 2.1
Name: mqt.qao
Version: 0.3.0
Summary: MQT Quantum Auto Optimizer: Automatic Framework for Solving Optimization Problems with Quantum Computers
Author-email: Deborah Volpe <deborah.volpe@polito.it>, Nils Quetschlich <nils.quetschlich@tum.de>
License: MIT License
Project-URL: Homepage, https://github.com/cda-tum/mqt-qao
Project-URL: Issues, https://github.com/cda-tum/mqt-qao/issues
Project-URL: Discussions, https://github.com/cda-tum/mqt-qao/discussions
Project-URL: Research, https://www.cda.cit.tum.de/research/quantum/
Keywords: MQT,quantum-computing,optimization,QUBO
Classifier: Development Status :: 4 - Beta
Classifier: Intended Audience :: Developers
Classifier: License :: OSI Approved :: MIT License
Classifier: Operating System :: Microsoft :: Windows
Classifier: Operating System :: MacOS
Classifier: Operating System :: POSIX :: Linux
Classifier: Programming Language :: Python :: 3 :: Only
Classifier: Programming Language :: Python :: 3.9
Classifier: Programming Language :: Python :: 3.10
Classifier: Programming Language :: Python :: 3.11
Classifier: Programming Language :: Python :: 3.12
Classifier: Programming Language :: Python :: 3.13
Classifier: Intended Audience :: Science/Research
Classifier: Natural Language :: English
Classifier: Topic :: Scientific/Engineering :: Electronic Design Automation (EDA)
Requires-Python: >=3.9
License-File: LICENSE
Requires-Dist: qiskit>=1.0
Requires-Dist: qiskit_optimization>=0.6
Requires-Dist: qiskit_aer>=0.15
Requires-Dist: pandas>=2.1.2
Requires-Dist: numpy>=1.26
Requires-Dist: qubovert>=1.2.5
Requires-Dist: matplotlib>=3.8
Requires-Dist: docplex>=2.21.207
Requires-Dist: dwave-system>=1.25.0
Requires-Dist: dwave-samplers>=1.3.0
Requires-Dist: scikit-learn>=1.4.2
Requires-Dist: networkx
Provides-Extra: test
Requires-Dist: pytest>=7.2; extra == "test"
Provides-Extra: coverage
Requires-Dist: mqt.qao[test]; extra == "coverage"
Requires-Dist: pytest-cov>=4; extra == "coverage"
Provides-Extra: docs
Requires-Dist: furo>=2023.9.10; extra == "docs"
Requires-Dist: setuptools-scm>=8.1; extra == "docs"
Requires-Dist: sphinxcontrib-bibtex>=2.4.2; extra == "docs"
Requires-Dist: sphinx-copybutton>=0.5; extra == "docs"
Requires-Dist: ipython; extra == "docs"
Requires-Dist: ipykernel; extra == "docs"
Requires-Dist: nbsphinx; extra == "docs"
Requires-Dist: sphinxext-opengraph>=0.9; extra == "docs"
Requires-Dist: sphinx-autodoc-typehints; extra == "docs"
Requires-Dist: qiskit[visualization]; extra == "docs"
Provides-Extra: dev
Requires-Dist: mqt.qao[coverage,docs]; extra == "dev"
